bigboat/__init__.py
bigboat/application.py
bigboat/client.py
bigboat/entity.py
bigboat/instance.py
bigboat/py.typed
bigboat/utils.py
bigboat-1.0.1.dist-info/LICENSE
bigboat-1.0.1.dist-info/METADATA
bigboat-1.0.1.dist-info/WHEEL
bigboat-1.0.1.dist-info/top_level.txt
bigboat-1.0.1.dist-info/RECORD
