Metadata-Version: 2.1
Name: bigboat
Version: 1.0.1
Summary: BigBoat docker dashboard API
Author-email: Leon Helwerda <l.s.helwerda@liacs.leidenuniv.nl>
License: Apache 2.0
Project-URL: Homepage, https://gros.liacs.nl
Project-URL: PyPI, https://pypi.python.org/pypi/bigboat
Project-URL: Source Code, https://github.com/grip-on-software/bigboat-python-api
Project-URL: Issues, https://github.com/grip-on-software/bigboat-python-api/issues
Project-URL: Pull Requests, https://github.com/grip-on-software/bigboat-python-api/pulls
Project-URL: CI: GitHub Actions, https://github.com/grip-on-software/bigboat-python-api/actions
Project-URL: CI: Coveralls, https://coveralls.io/github/grip-on-software/bigboat-python-api?branch=master
Project-URL: CI: SonarCloud, https://sonarcloud.io/project/overview?id=grip-on-software_bigboat-python-api
Keywords: docker dashboard,bigboat,api
Classifier: Development Status :: 5 - Production/Stable
Classifier: Environment :: Web Environment
Classifier: Intended Audience :: Developers
Classifier: License :: OSI Approved :: Apache Software License
Classifier: Operating System :: OS Independent
Classifier: Programming Language :: Python
Classifier: Programming Language :: Python :: 3
Classifier: Programming Language :: Python :: 3.8
Classifier: Programming Language :: Python :: 3.9
Classifier: Programming Language :: Python :: 3.10
Classifier: Programming Language :: Python :: 3.11
Classifier: Programming Language :: Python :: 3.12
Classifier: Topic :: Internet :: WWW/HTTP
Classifier: Topic :: Software Development :: Libraries :: Python Modules
Classifier: Topic :: Software Development :: Build Tools
Requires-Python: >=3.8
License-File: LICENSE
Requires-Dist: requests >=2.17.3
Requires-Dist: pyyaml >=3.12
